[{"date":"Thu, 16 May 2024 17:45:43 GMT","sloc":22,"lloc":12,"functions":6,"deliveredBugs":0.129,"difficulty":13.026,"maintainability":91.773,"lintErrors":8},{"date":"Thu, 16 May 2024 17:47:29 GMT","sloc":22,"lloc":12,"functions":6,"deliveredBugs":0.129,"difficulty":13.026,"maintainability":91.773,"lintErrors":8},{"date":"Thu, 16 May 2024 20:25:39 GMT","sloc":22,"lloc":12,"functions":6,"deliveredBugs":0.129,"difficulty":13.026,"maintainability":91.773,"lintErrors":8},{"date":"Thu, 16 May 2024 20:26:41 GMT","sloc":22,"lloc":12,"functions":6,"deliveredBugs":0.129,"difficulty":13.026,"maintainability":91.773,"lintErrors":8},{"date":"Thu, 16 May 2024 20:27:58 GMT","sloc":22,"lloc":12,"functions":6,"deliveredBugs":0.129,"difficulty":13.026,"maintainability":91.773,"lintErrors":8},{"date":"Fri, 17 May 2024 10:48:05 GMT","sloc":22,"lloc":12,"functions":6,"deliveredBugs":0.129,"difficulty":13.026,"maintainability":91.773,"lintErrors":8},{"date":"Fri, 17 May 2024 13:34:55 GMT","sloc":18,"lloc":11,"functions":4,"deliveredBugs":0.101,"difficulty":11.647,"maintainability":89.149,"lintErrors":6},{"date":"Fri, 17 May 2024 15:11:35 GMT","sloc":18,"lloc":11,"functions":4,"deliveredBugs":0.101,"difficulty":11.647,"maintainability":89.149,"lintErrors":6},{"date":"Fri, 17 May 2024 18:54:59 GMT","sloc":18,"lloc":11,"functions":4,"deliveredBugs":0.101,"difficulty":11.647,"maintainability":89.149,"lintErrors":6},{"date":"Fri, 17 May 2024 19:43:10 GMT","sloc":18,"lloc":11,"functions":4,"deliveredBugs":0.101,"difficulty":11.647,"maintainability":89.149,"lintErrors":6}]